CHANGES.rst
COPYING
MANIFEST.in
README.rst
requirements-dev.txt
requirements.txt
setup.cfg
setup.py
pelican_planet/__init__.py
pelican_planet/planet.py
pelican_planet/utils.py
pelican_planet.egg-info/PKG-INFO
pelican_planet.egg-info/SOURCES.txt
pelican_planet.egg-info/dependency_links.txt
pelican_planet.egg-info/not-zip-safe
pelican_planet.egg-info/requires.txt
pelican_planet.egg-info/top_level.txt
pelican_planet/tests/__init__.py
pelican_planet/tests/conftest.py
pelican_planet/tests/test_planet.py
pelican_planet/tests/test_utils.py
pelican_planet/tests/data/karadoc.atom.xml
pelican_planet/tests/data/perceval.atom.xml
pelican_planet/tests/data/planet.md.tmpl