Metadata-Version: 1.1
Name: pelican-planet
Version: 0.9.1
Summary: Blog aggregator plugin for Pelican
Home-page: https://framagit.org/bochecha/pelican-planet
Author: Mathieu Bridon
Author-email: bochecha@daitauha.fr
License: UNKNOWN
Platform: UNKNOWN
Classifier: Development Status :: 4 - Beta
Classifier: Framework :: Pelican :: Plugins
Classifier: License :: OSI Approved :: GNU Affero General Public License v3 or later (AGPLv3+)
Classifier: Programming Language :: Python :: 3.4
Classifier: Programming Language :: Python :: 3.5
Classifier: Programming Language :: Python :: 3.6
Classifier: Programming Language :: Python :: 3 :: Only
Classifier: Topic :: Internet :: WWW/HTTP
Classifier: Topic :: Internet :: WWW/HTTP :: Site Management
